<?xml version="1.0" encoding="utf-8"?>
<ModMetaData>
	<name>[1.0] Crystal Bodyparts</name>
	<author>FantasyFan</author>
	<targetVersion>1.0.2408</targetVersion>
	<description>
Have you ever wanted to create better prosthetics in medieval times. Now you can.

This mod adds ten different bodyparts:
-Crystal Leg (like Bionic Leg)
-Crystal Arm (like Bionic Arm)
-Crystal Eye (like Bionic Eye)
-Crystal Ear (like Bionic Ear)
-Crystal Heart (like Bionic Heart)
-Crystal Spine (like Bionic Spine)
-Crystal Jaw
-Crystal Liver
-Crystal Kidney
-Crystal Lung

This mod adds four advanced bodyparts:
-Adv. Crystal Leg (like Archotech Leg)
-Adv. Crystal Arm (like Archotech Arm)
-Adv. Crystal Eye (like Archotech Eye)
-Adv. Crystal Ear (like Archotech Ear)

Two new different workbenches:
-Crystal Growth Station
-Adv. Crystal Growth Station

Two research projects

One new ore:
-Blue crystal
-Purple crystal


Can be safely added to existing saves.


If you find things unbalanced, please make suggestions for improvement.
	</description>
</ModMetaData>